[{"id":"QvxzadRj0","title":"clientManage","name":"clientManage","route":["/QvxzadRj0"],"backgroundColor":"#ffffff","width":1440,"height":794,"pageSize":null,"type":"PolarBear"},{"id":"thycomhqjz","title":"clientManageInitCs","name":"clientManageInitCs","route":["/thycomhqjz"],"backgroundColor":"#ffffff","width":1440,"height":1080,"pageSize":null,"type":"PolarBear"},{"id":"xpZNKSm2dV","title":"clientUpdate","name":"clientUpdate","route":["/xpZNKSm2dV"],"backgroundColor":"#ffffff","width":1440,"height":500,"pageSize":null,"type":"PolarBear"},{"id":"cscTcnchOK","title":"composeTreeAuth","name":"composeTreeAuth","route":["/cscTcnchOK"],"backgroundColor":"#f4f7fa","width":1440,"height":600,"pageSize":null,"type":"PolarBear"},{"id":"curIgitogK","title":"dataAuth","name":"dataAuth","route":["/curIgitogK"],"backgroundColor":"#ffffff","width":1440,"height":550,"pageSize":null,"type":"PolarBear"},{"id":"SQJUXv8yBU","title":"dataAuthV2","name":"dataAuthV2","route":["/SQJUXv8yBU"],"backgroundColor":"#f4f7fa","width":1440,"height":880,"pageSize":null,"type":"PolarBear"},{"id":"vJ4SXwPvoN","title":"menuEdit","name":"menuEdit","route":["/vJ4SXwPvoN"],"backgroundColor":"#ffffff","width":1440,"height":1080,"pageSize":null,"type":"PolarBear"},{"id":"PL5tKFuKuF","title":"menuManage","name":"menuManage","route":["/PL5tKFuKuF"],"backgroundColor":"#ffffff","width":1440,"height":794,"pageSize":null,"type":"PolarBear"},{"id":"m1NFXdZUUA","title":"menuManageEdit","name":"menuManageEdit","route":["/m1NFXdZUUA"],"backgroundColor":"#ffffff","width":1440,"height":1080,"pageSize":null,"type":"PolarBear"},{"id":"tFGOfcyN4a","title":"queryTimeAuth","name":"queryTimeAuth","route":["/tFGOfcyN4a"],"backgroundColor":"#f4f7fa","width":1440,"height":495,"pageSize":null,"type":"PolarBear"},{"id":"99dcTJScS2","title":"roleAuth","name":"roleAuth","route":["/99dcTJScS2"],"backgroundColor":"#ffffff","width":1440,"height":850,"pageSize":null,"type":"PolarBear"},{"id":"1_ghSlIw3k","title":"roleManage","name":"roleManage","route":["/1_ghSlIw3k"],"backgroundColor":"#ffffff","width":1440,"height":794,"pageSize":null,"type":"PolarBear"},{"id":"yv5LcZHKSb","title":"roleManageEdit","name":"roleManageEdit","route":["/yv5LcZHKSb"],"backgroundColor":"#ffffff","width":1440,"height":800,"pageSize":null,"type":"PolarBear"},{"id":"cvbRiNKcIq","title":"userManage","name":"userManage","route":["/cvbRiNKcIq"],"backgroundColor":"#ffffff","width":1440,"height":794,"pageSize":null,"type":"PolarBear"},{"id":"c4GkafIFbp","title":"userManageAuth","name":"userManageAuth","route":["/c4GkafIFbp"],"backgroundColor":"#ffffff","width":1440,"height":600,"pageSize":null,"type":"PolarBear"},{"id":"tpcaTWF-u0","title":"userManageCopyAuth","name":"userManageCopyAuth","route":["/tpcaTWF-u0"],"backgroundColor":"#f8f8f8","width":1240,"height":877,"pageSize":null,"type":"PolarBear"},{"id":"odfivVs2zdF","title":"userManageEdit","name":"userManageEdit","route":["/odfivVs2zdF"],"backgroundColor":"#ffffff","width":1440,"height":1080,"pageSize":null,"type":"PolarBear"},{"id":"3UxoGMqTuGA","title":"userManageInitPsd","name":"userManageInitPsd","route":["/3UxoGMqTuGA"],"backgroundColor":"#ffffff","width":1440,"height":1080,"pageSize":null,"type":"PolarBear"},{"id":"xEt0-QUPR7C","title":"userManageRoleAuth","name":"userManageRoleAuth","route":["/xEt0-QUPR7C"],"backgroundColor":"#ffffff","width":1440,"height":794,"pageSize":null,"type":"PolarBear"}]
